{
  "type": "minecraft:command",
  "pools": [
    {
      "rolls": 1,
      "entries": [
        {
          "type": "minecraft:item",
          "name": "minecraft:bow",
          "functions": [
            {
              "function": "minecraft:set_enchantments",
              "enchantments": {
                "minecraft:power": 1
              }
            }
          ]
        }
      ]
    },
    {
      "rolls": 1,
      "entries": [
        {
          "type": "minecraft:item",
          "name": "minecraft:bow",
          "functions": [
            {
              "function": "minecraft:set_enchantments",
              "enchantments": {
                "minecraft:punch": 1
              }
            }
          ]
        }
      ]
    },
    {
      "rolls": 1,
      "entries": [
        {
          "type": "minecraft:item",
          "name": "minecraft:arrow",
          "functions": [
            {
              "function": "minecraft:set_count",
              "count": 16
            }
          ]
        }
      ]
    },
    {
      "rolls": 1,
      "entries": [
        {
          "type": "minecraft:item",
          "name": "minecraft:spectral_arrow",
          "functions": [
            {
              "function": "minecraft:set_count",
              "count": 4
            }
          ]
        }
      ]
    },
    {
      "rolls": 1,
      "entries": [
        {
          "type": "minecraft:item",
          "name": "minecraft:tipped_arrow",
          "functions": [
            {
              "function": "minecraft:set_count",
              "count": 2
            },
            {
              "function": "minecraft:set_potion",
              "id": "minecraft:weakness"
            }
          ]
        }
      ]
    },
    {
      "rolls": 1,
      "entries": [
        {
          "type": "minecraft:item",
          "name": "minecraft:tipped_arrow",
          "functions": [
            {
              "function": "minecraft:set_count",
              "count": 2
            },
            {
              "function": "minecraft:set_potion",
              "id": "minecraft:slowness"
            }
          ]
        }
      ]
    },
    {
      "rolls": 1,
      "entries": [
        {
          "type": "minecraft:item",
          "name": "minecraft:oak_leaves",
          "functions": [
            {
              "function": "minecraft:set_count",
              "count": 20
            }
          ]
        }
      ]
    },
    {
      "rolls": 1,
      "entries": [
        {
          "type": "minecraft:item",
          "name": "minecraft:cooked_rabbit",
          "functions": [
            {
              "function": "minecraft:set_count",
              "count": 8
            }
          ]
        }
      ]
    }
  ]
}